[
    {
        "cover": "/assets/200001-3.jpg",
        "artist": "Boney M.",
        "title": "For Dancin'",
        "year": 2000,
        "rating": 5,
        "label": "Italy & C",
        "country": null,
        "format": "CDr, Album, Unofficial Release ",
        "genre": "Electronic",
        "style": "Disko",
        "tracklist": {
            "1": "Felicidad (Margherita) (Long Version)",
            "2": "Strange",
            "3": "Gadda - Da - Vida (Long Version)",
            "4": "Children Of Paradise (Long Version)"
        },
        "tracktime": {
            "1": "11:47",
            "2": "3:30",
            "3": "8:55",
            "4": "5:20"
        },
        "credits": "Producer - Frank Farian",
        "notes": "Digital Remastering from Original Vinyl",
        "id": "200001-3"
    },
    {
        "cover": "/assets/200201-2.jpg",
        "artist": "Marcella Bella",
        "title": "Marcella Bella",
        "year": 2002,
        "rating": 5,
        "label": "Italy & C",
        "country": null,
        "format": "CDr, Album, Unofficial Release ",
        "genre": "Pop",
        "style": "Europop",
        "tracklist": {
            "1": "Canto Straniero",
            "2": "Strange",
            "3": "Rio De Janeiro",
            "4": "Oh, Johnny",
            "5": "Baciami",
            "6": "Malinconia",
            "7": "Pensa Per Te",
            "8": "Una Vampata Di Te",
            "9": "Coriandoli",
            "10": "Cosi Piccolo"
        },
        "tracktime": {
            "1": "4:00",
            "2": "4:15",
            "3": "3:54",
            "4": "3:58",
            "5": "4:02",
            "6": "4:45",
            "7": "3:30",
            "8": "3:36",
            "9": "3:46",
            "10": "4:34"
        },
        "credits": "Arranged By – Beppe Cantarelli, Dario Baldan Bembo, Tony Mimms, Producer – Gianni Bella",
        "notes": "Digital Remastering from Original Vinyl",
        "id": "200201-2"
    }
]